uutils/__init__.py
uutils/emailing.py
uutils/logger.py
uutils/stats_collector_mit.py
uutils/argparse_uu/__init__.py
uutils/argparse_uu/args_tinfer.py
uutils/argparse_uu/common.py
uutils/argparse_uu/meta_learning.py
uutils/argparse_uu/supervised_learning.py
uutils/hf_uu/__init__.py
uutils/hf_uu/common.py
uutils/hf_uu/data_hf/__init__.py
uutils/hf_uu/data_hf/common.py
uutils/hf_uu/hf_argparse/__init__.py
uutils/hf_uu/hf_argparse/args_alpaca.py
uutils/hf_uu/hf_argparse/args_alpaca_farm.py
uutils/hf_uu/hf_argparse/common.py
uutils/hf_uu/hf_argparse/falcon_uu_training_args.py
uutils/hf_uu/inference_uu/__init__.py
uutils/hf_uu/mains_hf/__init__.py
uutils/hf_uu/mains_hf/falcon_uu/__init__.py
uutils/hf_uu/mains_hf/falcon_uu/main_falcon_uu.py
uutils/hf_uu/model_tokenizer/__init__.py
uutils/hf_uu/model_tokenizer/alpaca_uu.py
uutils/hf_uu/model_tokenizer/camel_hf_uu.py
uutils/hf_uu/model_tokenizer/falcon_guanaco.py
uutils/hf_uu/model_tokenizer/falcon_uu_mdl_tok.py
uutils/hf_uu/model_tokenizer/init_new_token_in_model.py
uutils/hf_uu/train/__init__.py
uutils/hf_uu/train/common.py
uutils/hf_uu/train/full_fine_tuning.py
uutils/hf_uu/train/train_causal.py
uutils/hf_uu/train/train_seq2seq.py
uutils/hf_uu/train/sft/__init__.py
uutils/hf_uu/train/sft/falcon_lambda_labs.py
uutils/hf_uu/train/sft/falcon_peft.py
uutils/hf_uu/train/sft/qlora_ft.py
uutils/jax_uu/__init__.py
uutils/jax_uu/models/__init__.py
uutils/jax_uu/models/flash_attn.py
uutils/jax_uu/models/layer_norm_autoregressive.py
uutils/jax_uu/models/mha_simple.py
uutils/logging_uu/__init__.py
uutils/logging_uu/wandb_logging/__init__.py
uutils/logging_uu/wandb_logging/common.py
uutils/logging_uu/wandb_logging/supervised_learning.py
uutils/numpy_uu/__init__.py
uutils/numpy_uu/common.py
uutils/plot/__init__.py
uutils/plot/histograms_uu.py
uutils/plot/image_visualization.py
uutils/stats_uu/__init__.py
uutils/stats_uu/ci_uu.py
uutils/stats_uu/effect_size.py
uutils/stats_uu/overfitting.py
uutils/stats_uu/power.py
ultimate_utils-0.7.0.dist-info/LICENSE
ultimate_utils-0.7.0.dist-info/METADATA
ultimate_utils-0.7.0.dist-info/WHEEL
ultimate_utils-0.7.0.dist-info/top_level.txt
ultimate_utils-0.7.0.dist-info/RECORD
