Metadata-Version: 2.1
Name: ultimate-utils
Version: 0.7.0
Summary: Brando's ultimate utils for science, machine learning and AI
Home-page: https://github.com/brando90/ultimate-utils
Author: Brando Miranda
Author-email: brandojazz@gmail.com
License: MIT
Requires-Python: >=3.9.0
License-File: LICENSE
Requires-Dist: dill
Requires-Dist: networkx (>=2.5)
Requires-Dist: scipy
Requires-Dist: scikit-learn
Requires-Dist: lark-parser
Requires-Dist: tensorboard
Requires-Dist: pandas
Requires-Dist: progressbar2
Requires-Dist: transformers
Requires-Dist: datasets
Requires-Dist: requests
Requires-Dist: aiohttp
Requires-Dist: numpy
Requires-Dist: plotly
Requires-Dist: wandb
Requires-Dist: matplotlib
Requires-Dist: twine
Requires-Dist: fairseq
